imageit/__init__.py
imageit/admin.py
imageit/apps.py
imageit/fields.py
imageit/filetypes.py
imageit/models.py
imageit/settings.py
imageit/utils.py
imageit/views.py
imageit/widgets.py
imageit/static/imageit/dist/css/imageit.css
imageit/static/imageit/dist/img/folder.svg
imageit/static/imageit/dist/img/image-icon.svg
imageit/static/imageit/dist/img/upload.svg
imageit/static/imageit/dist/js/imageit.js
imageit/templates/imageit/widgets/crop_it_widget.html
imageit/templates/imageit/widgets/scale_it_widget.html
django_imageit-0.0.8.dist-info/LICENSE
django_imageit-0.0.8.dist-info/METADATA
django_imageit-0.0.8.dist-info/WHEEL
django_imageit-0.0.8.dist-info/top_level.txt
django_imageit-0.0.8.dist-info/RECORD
