Metadata-Version: 2.1
Name: django-imageit
Version: 0.0.8
Summary: Image upload & processing plugin built for Django
Home-page: https://github.com/byite/django-imageit
Author: Scott James
Author-email: scottjames@byitegroup.com
License: UNKNOWN
Keywords: django images imageit image upload scale crop resize
Platform: UNKNOWN
Classifier: Intended Audience :: Developers
Classifier: License :: OSI Approved :: MIT License
Classifier: Operating System :: OS Independent
Classifier: Programming Language :: Python :: 3
Classifier: Programming Language :: Python :: 3.6
Classifier: Programming Language :: Python :: 3.7
Classifier: Programming Language :: Python :: 3.8
Classifier: Programming Language :: Python :: 3.9
Classifier: Programming Language :: JavaScript
Classifier: Framework :: Django :: 3.0
Classifier: Framework :: Django :: 3.1
Classifier: Framework :: Django :: 3.2
Classifier: Topic :: Software Development :: Libraries :: Python Modules
Classifier: Topic :: Multimedia :: Graphics
Classifier: Topic :: Multimedia :: Graphics :: Presentation
Requires-Dist: django (>=3)
Requires-Dist: pillow (>8.0.0)
Requires-Dist: filetype (>1.0.0)
Provides-Extra: dev
Requires-Dist: twine (>=3.4) ; extra == 'dev'
